{
  "$schema": "https://raw.githubusercontent.com/Cencosud-X/seki-schemas/main/v1/projects/typerc.schema.json",
  "name": "Module Implementation",
  "tags": [
    "Globalization",
    "Yumi",
    "Module",
    "experimental"
  ],
  "kind": "price-reduction-mobile-implementation",
  "folder": "libs",
  "icons": {
    "light": "icons/icon.svg",
    "dark": "icons/icon.svg"
  },
  "descriptions": {
    "en": "The price reduction module is a functionality that enables the in-store replenisher to request a price reduction for a product from the central administration through the application, based on various reasons.",
    "es": "El módulo baja de precio es una funcionalidad que permite al reponedor en sala solicitar a administración central la baja de precio de un producto desde la aplicación en base a diversos motivos"
  },
  "scripts": {
    "pre": "scripts/pre.js",
    "rollback": "scripts/rollback.js",
    "post": "scripts/post.js"
  },
  "interpolations": {
    "source": "template",
    "substitutions": {}
  },
  "display_name": "Price Reduction Mobile"
}